odoo8_addon_report_custom_filename-8.0.1.0.1.99.dev7-py2.7-nspkg.pth
odoo8_addon_report_custom_filename-8.0.1.0.1.99.dev7.dist-info/DESCRIPTION.rst
odoo8_addon_report_custom_filename-8.0.1.0.1.99.dev7.dist-info/METADATA
odoo8_addon_report_custom_filename-8.0.1.0.1.99.dev7.dist-info/RECORD
odoo8_addon_report_custom_filename-8.0.1.0.1.99.dev7.dist-info/WHEEL
odoo8_addon_report_custom_filename-8.0.1.0.1.99.dev7.dist-info/metadata.json
odoo8_addon_report_custom_filename-8.0.1.0.1.99.dev7.dist-info/namespace_packages.txt
odoo8_addon_report_custom_filename-8.0.1.0.1.99.dev7.dist-info/top_level.txt
odoo_addons/report_custom_filename/README.rst
odoo_addons/report_custom_filename/__init__.py
odoo_addons/report_custom_filename/__openerp__.py
odoo_addons/report_custom_filename/controllers/__init__.py
odoo_addons/report_custom_filename/controllers/report_controller.py
odoo_addons/report_custom_filename/controllers/reports.py
odoo_addons/report_custom_filename/i18n/ca.po
odoo_addons/report_custom_filename/i18n/de.po
odoo_addons/report_custom_filename/i18n/es.po
odoo_addons/report_custom_filename/i18n/pt_PT.po
odoo_addons/report_custom_filename/i18n/report_custom_filename.pot
odoo_addons/report_custom_filename/i18n/sl.po
odoo_addons/report_custom_filename/i18n/tr_TR.po
odoo_addons/report_custom_filename/model/__init__.py
odoo_addons/report_custom_filename/model/ir_actions_report_xml.py
odoo_addons/report_custom_filename/static/description/icon.png
odoo_addons/report_custom_filename/view/ir_actions_report_xml.xml
